<?xml version="1.0" encoding="UTF-8"?>
<root BTCPP_format="4">
  <BehaviorTree ID="blue_panel_simple">
    <TaskSequence>
      <Script code="is_pick_first:=true"/>
      <Script code="is_pick_second:=true"/>
      <ForceSuccess>
        <RetryUntilSuccessful num_attempts="6">
          <Fallback>
            <Move goal="0.815; -0.6;90"
                  ignore_obstacles="true"
                  linear_velocity="0.7"
                  frame_id="map"
                  angular_velocity="1.8"
                  mode="7"
                  linear_acceleration="0.5"
                  angular_acceleration="0.1"/>
            <ForceFailure>
              <Sleep msec="500"/>
            </ForceFailure>
          </Fallback>
        </RetryUntilSuccessful>
      </ForceSuccess>
      <ScoreboardTask points="15"
                      task="SOLAR_PANELS"/>
      <ForceSuccess>
        <Sequence>
          <Sequence _onFailure="is_pick_first=false">
            <RetryUntilSuccessful num_attempts="5">
              <Fallback>
                <Move goal="225"
                      ignore_obstacles="false"
                      linear_velocity="1.5"
                      frame_id="map"
                      angular_velocity="2.5"
                      mode="4"
                      linear_acceleration="1.0"
                      angular_acceleration="2.2"/>
                <Sleep msec="500"/>
              </Fallback>
            </RetryUntilSuccessful>
            <Parallel failure_count="1"
                      success_count="-1">
              <SubTree ID="drop_fork_down"
                       _autoremap="true"/>
              <SubTree ID="gentle_attack"
                       linear_velocity="1.5"
                       linear_acceleration="1.4"
                       type="3"
                       goal="0.25;-0.9;90"/>
            </Parallel>
            <SubTree ID="gentle_attack"
                     goal="0.25;-0.8;90"
                     linear_acceleration="1.4"
                     linear_velocity="1.5"
                     type="3"/>
            <SubTree ID="gentle_attack"
                     type="3"
                     linear_velocity="1.2"
                     linear_acceleration="1.0"
                     goal="0.25;-0.63;90"/>
          </Sequence>
          <SubTree ID="try_pick_up_weed_front"
                   _autoremap="true"/>
        </Sequence>
      </ForceSuccess>
      <ForceSuccess name="ForceSuccess#0"
                    _onFailure="is_pick_second=false">
        <Sequence>
          <Sequence>
            <RetryUntilSuccessful num_attempts="5">
              <Fallback>
                <Move goal="-135"
                      ignore_obstacles="false"
                      linear_velocity="1.5"
                      frame_id="map"
                      angular_velocity="2.5"
                      mode="4"
                      linear_acceleration="1.0"
                      angular_acceleration="2.2"/>
                <Sleep msec="500"/>
              </Fallback>
            </RetryUntilSuccessful>
            <SubTree ID="gentle_attack"
                     type="7"
                     linear_velocity="1.5"
                     linear_acceleration="1.4"
                     goal="-0.30;-1.0;-90"/>
            <SubTree ID="gentle_attack"
                     type="3"
                     linear_velocity="1.5"
                     linear_acceleration="1.4"
                     goal="-0.25;-0.75;-90"
                     _autoremap="true"/>
            <SubTree ID="gentle_attack"
                     type="3"
                     linear_velocity="1.2"
                     linear_acceleration="1.0"
                     goal="-0.25;-0.64;-90"/>
          </Sequence>
          <SubTree ID="try_pick_up_weed_back"
                   _autoremap="true"/>
        </Sequence>
      </ForceSuccess>
      <ForceSuccess name="ForceSuccess#1"
                    _skipIf="is_pick_second==false">
        <SubTree ID="try_put_plenter_back"
                 _autoremap="true"/>
      </ForceSuccess>
      <ForceSuccess name="ForceSuccess#2"
                    _skipIf="is_pick_first==false">
        <SubTree ID="try_pick_up_pots_with_fork"
                 _autoremap="true"/>
      </ForceSuccess>
    </TaskSequence>
  </BehaviorTree>

  <!-- Description of Node Models (used by Groot) -->
  <TreeNodesModel>
    <Action ID="Move"
            editable="true">
      <input_port name="goal"/>
      <inout_port name="ignore_obstacles"
                  default="true"/>
      <input_port name="linear_velocity"
                  default="0.5"/>
      <input_port name="frame_id"
                  default="map"/>
      <input_port name="angular_velocity"
                  default="1.0"/>
      <input_port name="mode"
                  default="7"/>
      <input_port name="linear_acceleration"
                  default="0.8"/>
      <input_port name="angular_acceleration"
                  default="1.8"/>
    </Action>
    <Action ID="ScoreboardTask"
            editable="true">
      <input_port name="points"
                  default="0">points scored, can be negative</input_port>
      <input_port name="task"
                  default="store_sample_to_work_shed">unique task name</input_port>
    </Action>
    <Control ID="TaskSequence"
             editable="true"/>
  </TreeNodesModel>

</root>
